{
  "id": "li-konso-2006181000",
  "type": "statute",
  "title": "Kundmachung vom 23. August 2006 der Beschlüsse Nr. 56/2006 bis 58/2006, 60/2006 bis 63/2006, 66/2006, 70/2006, 71/2006 und 73/2006 bis 75/2006 des Gemeinsamen EWR-Ausschusses",
  "title_en": "",
  "short_name": "LGBl 2006.181",
  "status": "in_force",
  "issued_date": "2006-08-23",
  "in_force_date": "2006-08-23",
  "url": "https://www.gesetze.li/konso/2006181000",
  "description": "Kundmachung vom 23. August 2006 der Beschlüsse Nr. 56/2006 bis 58/2006, 60/2006 bis 63/2006, 66/2006, 70/2006, 71/2006 und 73/2006 bis 75/2006 des Gemeinsamen EWR-Ausschusses",
  "provisions": [
    {
      "provision_ref": "art1",
      "chapter": "Anhang 1",
      "section": "1",
      "title": "Art. 1",
      "content": "In Anhang II Kapitel XV des Abkommens werden unter Nummer 12a (Richtlinie 91/414/EWG des Rates) folgende Gedankenstriche angefügt:\n\"- 32005 L 0053: Richtlinie 2005/53/EG der Kommission vom 16. September 2005 ( ABl. L 241 vom 17.9.2005, S. 51 ),\n- 32005 L 0054: Richtlinie 2005/54/EG der Kommission vom 19. September 2005 ( ABl. L 244 vom 20.9.2005, S. 21 ),\n- 32005 L 0057: Richtlinie 2005/57/EG der Kommission vom 21. September 2005 ( ABl. L 246 vom 22.9.2005, S. 14 ),\n- 32005 L 0058: Richtlinie 2005/58/EG der Kommission vom 21. September 2005 ( ABl. L 246 vom 22.9.2005, S. 17 ),\n- 32005 L 0072: Richtlinie 2005/72/EG der Kommission vom 21. Oktober 2005 ( ABl. L 279 vom 22.10.2005, S. 63 ),\n- 32006 L 0005: Richtlinie 2006/5/EG der Kommission vom 17. Januar 2006 ( ABl. L 12 vom 18.1.2006, S. 17 ),\n- 32006 L 0006: Richtlinie 2006/6/EG der Kommission vom 17. Januar 2006 ( ABl. L 12 vom 18.1.2006, S. 21 ).\""
    },
    {
      "provision_ref": "art2",
      "chapter": "Anhang 1",
      "section": "2",
      "title": "Art. 2",
      "content": "Die isländische und norwegische Sprachfassung der Richtlinien 2005/53/EG, 2005/54/EG, 2005/55/EG, 2005/57/EG, 2005/58/EG, 2005/72/EG, 2006/5/EG und 2006/6/EG, die in der EWR-Beilage des Amtsblattes der Europäischen Union veröffentlicht wird, ist verbindlich."
    },
    {
      "provision_ref": "art3",
      "chapter": "Anhang 1",
      "section": "3",
      "title": "Art. 3",
      "content": "Dieser Beschluss tritt am 3. Juni 2006 in Kraft, sofern dem Gemeinsamen EWR-Ausschuss alle Mitteilungen nach Art. 103 Abs. 1 des Abkommens vorliegen ."
    },
    {
      "provision_ref": "art4",
      "chapter": "Anhang 1",
      "section": "4",
      "title": "Art. 4",
      "content": "Dieser Beschluss wird im EWR-Abschnitt und in der EWR-Beilage des Amtsblattes der Europäischen Union veröffentlicht.\nGeschehen zu Brüssel am 2. Juni 2006\n(Es folgen die Unterschriften)\nAnhang 2\nBeschluss des Gemeinsamen EWR-Ausschusses Nr. 57/2006\nvom 2. Juni 2006\nzur Änderung des Anhangs II (Technische Vorschriften, Normen, Prüfung und Zertifizierung) des EWR-Abkommens\nDer Gemeinsame EWR-Ausschuss -\ngestützt auf das Abkommen über den Europäischen Wirtschaftsraum, geändert durch das Anpassungsprotokoll zum Abkommen über den Europäischen Wirtschaftsraum (nachstehend \"Abkommen\" genannt), insbesondere auf Art. 98,\nin Erwägung nachstehender Gründe:\n1. Anhang II des Abkommens wurde durch den Beschluss des Gemeinsamen EWR-Ausschusses Nr. 101/2005 vom 8. Juli 2005 geändert .\n2. Die Entscheidung 2005/631/EG der Kommission vom 29. August 2005 über grundlegende Anforderungen im Sinne der Richtlinie 1999/5/EG des Europäischen Parlaments und des Rates zur Sicherstellung des Zugangs von Cospas-Sarsat-Ortungsbaken zu Notfalldiensten ist in das Abkommen aufzunehmen -\nbeschliesst:"
    }
  ],
  "definitions": []
}
