{
  "id": "li-konso-2001007000",
  "type": "statute",
  "title": "Kundmachung vom 9. Januar 2001 des Beschlusses Nr. 59/2000 des Gemeinsamen EWR-Ausschusses",
  "title_en": "",
  "short_name": "LGBl 2001.007",
  "status": "in_force",
  "issued_date": "2001-01-09",
  "in_force_date": "2001-01-09",
  "url": "https://www.gesetze.li/konso/2001007000",
  "description": "Kundmachung vom 9. Januar 2001 des Beschlusses Nr. 59/2000 des Gemeinsamen EWR-Ausschusses",
  "provisions": [
    {
      "provision_ref": "art1",
      "chapter": "Anhang",
      "section": "1",
      "title": "Art. 1",
      "content": "In Anhang III des Abkommens wird unter \"Rechtsakt, auf den Bezug genommen wird\" (Richtlinie 85/374/EWG des Rates) Folgendes angefügt:\n\", geändert durch:\n- 399 L 0034 : Richtlinie 1999/34/EG des Europäischen Parlaments und des Rates vom 10. Mai 1999 ( ABl. L 141 vom 4.6.1999, S. 20 ).\""
    },
    {
      "provision_ref": "art2",
      "chapter": "Anhang",
      "section": "2",
      "title": "Art. 2",
      "content": "Der Wortlaut der Richtlinie 1999/34/EG des Europäischen Parlaments und des Rates in isländischer und norwegischer Sprache, der im EWR-Supplement des Amtsblatts der Europäischen Gemeinschaften veröffentlicht wird, ist verbindlich."
    },
    {
      "provision_ref": "art3",
      "chapter": "Anhang",
      "section": "3",
      "title": "Art. 3",
      "content": "Dieser Beschluss tritt am 29. Juni 2000 in Kraft, sofern dem Gemeinsamen EWR-Ausschuss alle Mitteilungen nach Art. 103 Abs. 1 des Abkommens vorliegen ."
    },
    {
      "provision_ref": "art4",
      "chapter": "Anhang",
      "section": "4",
      "title": "Art. 4",
      "content": "Dieser Beschluss wird im EWR-Abschnitt und im EWR-Supplement des Amtsblatts der Europäischen Gemeinschaftenveröffentlicht.\nBrüssel, den 28. Juni 2000\n(Es folgen die Unterschriften)\n1\nABl. L 141 vom 4.6.1999, S. 20 .\n2\nDas Bestehen verfassungsrechtlicher Anforderungen wurde mitgeteilt."
    }
  ],
  "definitions": []
}
