{
  "id": "li-konso-2022385000",
  "type": "statute",
  "title": "Kundmachung vom 13. Dezember 2022 des Beschlusses Nr. 177/2021 des Gemeinsamen EWR-Ausschusses",
  "title_en": "",
  "short_name": "LGBl 2022.385",
  "status": "in_force",
  "issued_date": "2022-12-13",
  "in_force_date": "2022-12-13",
  "url": "https://www.gesetze.li/konso/2022385000",
  "description": "Kundmachung vom 13. Dezember 2022 des Beschlusses Nr. 177/2021 des Gemeinsamen EWR-Ausschusses",
  "provisions": [
    {
      "provision_ref": "art1",
      "chapter": "Anhang",
      "section": "1",
      "title": "Art. 1",
      "content": "In Anhang XVIII des EWR-Abkommens wird unter Nummer 15 (Richtlinie 2000/54/EG des Europäischen Parlaments und des Rates) Folgendes angefügt:\n\", geändert durch:\n- 32020 L 0739 : Richtlinie (EU) 2020/739 der Kommission vom 3. Juni 2020 (ABl. L 175 vom 4.6.2020, S. 11) .\""
    },
    {
      "provision_ref": "art2",
      "chapter": "Anhang",
      "section": "2",
      "title": "Art. 2",
      "content": "Der Wortlaut der Richtlinie (EU) 2020/739 in isländischer und norwegischer Sprache, der in der EWR-Beilage des Amtsblattes der Europäischen Union veröffentlicht wird, ist verbindlich."
    },
    {
      "provision_ref": "art3",
      "chapter": "Anhang",
      "section": "3",
      "title": "Art. 3",
      "content": "Dieser Beschluss tritt am 12. Juni 2021 in Kraft, sofern alle Mitteilungen nach Art. 103 Abs. 1 des EWR-Abkommens vorliegen , oder am Tag des Inkrafttretens des Beschlusses des Gemeinsamen EWR-Ausschusses, mit dem die Richtlinie (EU) 2019/1833 der Kommission in das EWR-Abkommen aufgenommen wurde, je nachdem welcher Zeitpunkt der spätere ist."
    },
    {
      "provision_ref": "art4",
      "chapter": "Anhang",
      "section": "4",
      "title": "Art. 4",
      "content": "Dieser Beschluss wird im EWR-Abschnitt und in der EWR-Beilage des Amtsblattes der Europäischen Union veröffentlicht.\nGeschehen zu Brüssel am 11. Juni 2021.\n(Es folgen die Unterschriften)\n1\nABl. L 175 vom 4.6.2020, S. 11 .\n2\nEin Bestehen verfassungsrechtlicher Anforderungen wurde nicht mitgeteilt."
    }
  ],
  "definitions": []
}
