{
  "id": "li-konso-2007107000",
  "type": "statute",
  "title": "Kundmachung vom 8. Mai 2007 des Beschlusses Nr. 120/2005 des Gemeinsamen EWR-Ausschusses",
  "title_en": "",
  "short_name": "LGBl 2007.107",
  "status": "in_force",
  "issued_date": "2007-05-08",
  "in_force_date": "2007-05-08",
  "url": "https://www.gesetze.li/konso/2007107000",
  "description": "Kundmachung vom 8. Mai 2007 des Beschlusses Nr. 120/2005 des Gemeinsamen EWR-Ausschusses",
  "provisions": [
    {
      "provision_ref": "art1",
      "chapter": "Anhang",
      "section": "1",
      "title": "Art. 1",
      "content": "Anhang IX des Abkommens wird wie folgt geändert:\n1. Nach Nummer 29f (Richtlinie 2004/72/EG der Kommission) wird folgende Nummer eingefügt:\n\"29g. 32004 L 0109: Richtlinie 2004/109/EG des Europäischen Parlaments und des Rates vom 15. Dezember 2004 zur Harmonisierung der Transparenzanforderungen in Bezug auf Informationen über Emittenten, deren Wertpapiere zum Handel auf einem geregelten Markt zugelassen sind, und zur Änderung der Richtlinie 2001/34/EG ( ABl. L 390 vom 31.12.2004, S. 38 ).\"\n2. Unter Nummer 24 (Richtlinie 2001/34/EG des Europäischen Parlaments und des Rates) wird folgender Gedankenstrich eingefügt:\n\"- 32004 L 0109: Richtlinie 2004/109/EG des Europäischen Parlaments und des Rates vom 15. Dezember 2004 ( ABl. L 390 vom 31.12.2004, S. 38 ).\""
    },
    {
      "provision_ref": "art2",
      "chapter": "Anhang",
      "section": "2",
      "title": "Art. 2",
      "content": "Der Wortlaut der Richtlinie 2004/109/EG in isländischer und norwegischer Sprache, der in der EWR-Beilage des Amtsblattes der Europäischen Union veröffentlicht wird, ist verbindlich."
    },
    {
      "provision_ref": "art3",
      "chapter": "Anhang",
      "section": "3",
      "title": "Art. 3",
      "content": "Dieser Beschluss tritt am 1. Oktober 2005 in Kraft, sofern dem Gemeinsamen EWR-Ausschuss alle Mitteilungen nach Art. 103 Abs. 1 des Abkommens vorliegen ."
    },
    {
      "provision_ref": "art4",
      "chapter": "Anhang",
      "section": "4",
      "title": "Art. 4",
      "content": "Dieser Beschluss wird im EWR-Abschnitt und in der EWR-Beilage des Amtsblattes der Europäischen Union veröffentlicht.\nBrüssel, den 30. September 2005.\n(Es folgen die Unterschriften)\n1\nLR 170.50\n2\nABl. L 306 vom 24.11.2005, S. 45 .\n3\nABl. L 390 vom 31.12.2004, S. 38 .\n4\nEs wurden verfassungsrechtliche Anforderungen mitgeteilt."
    }
  ],
  "definitions": []
}
