{
  "id": "li-konso-2018455000",
  "type": "statute",
  "title": "Kundmachung vom 18. Dezember 2018 der Beschlüsse Nr. 52/2017 bis 56/2017, 58/2017, 61/2017, 62/2017, 66/2017 und 67/2017 des Gemeinsamen EWR-Ausschusses",
  "title_en": "",
  "short_name": "LGBl 2018.455",
  "status": "in_force",
  "issued_date": "2018-12-18",
  "in_force_date": "2018-12-18",
  "url": "https://www.gesetze.li/konso/2018455000",
  "description": "Kundmachung vom 18. Dezember 2018 der Beschlüsse Nr. 52/2017 bis 56/2017, 58/2017, 61/2017, 62/2017, 66/2017 und 67/2017 des Gemeinsamen EWR-Ausschusses",
  "provisions": [
    {
      "provision_ref": "art1",
      "chapter": "Anhang 1",
      "section": "1",
      "title": "Art. 1",
      "content": "In Anhang II Kapitel XIII des EWR-Abkommens wird unter Nummer 13 (Verordnung (EU) Nr. 37/2010 der Kommission) folgender Gedankenstrich angefügt:\n\"- 32016 R 1834 : Durchführungsverordnung (EU) 2016/1834 der Kommission vom 17. Oktober 2016 (ABl. L 280 vom 18.10.2016, S. 22) \""
    },
    {
      "provision_ref": "art2",
      "chapter": "Anhang 1",
      "section": "2",
      "title": "Art. 2",
      "content": "Der Wortlaut der Durchführungsverordnung (EU) 2016/1834 in isländischer und norwegischer Sprache, der in der EWR-Beilage des Amtsblattes der Europäischen Union veröffentlicht wird, ist verbindlich."
    },
    {
      "provision_ref": "art3",
      "chapter": "Anhang 1",
      "section": "3",
      "title": "Art. 3",
      "content": "Dieser Beschluss tritt am 18. März 2017 in Kraft, sofern alle Mitteilungen nach Art. 103 Abs. 1 des EWR-Abkommens vorliegen ."
    },
    {
      "provision_ref": "art4",
      "chapter": "Anhang 1",
      "section": "4",
      "title": "Art. 4",
      "content": "Dieser Beschluss wird im EWR-Abschnitt und in der EWR-Beilage des Amtsblattes der Europäischen Union veröffentlicht.\nGeschehen zu Brüssel am 17. März 2017.\n(Es folgen die Unterschriften)\nAnhang 2\nBeschluss des Gemeinsamen EWR-Ausschusses Nr. 53/2017\nvom 17. März 2017\nzur Änderung von Anhang II (Technische Vorschriften, Normen, Prüfung und Zertifizierung) des EWR-Abkommens\nDer Gemeinsame EWR-Ausschuss -\ngestützt auf das Abkommen über den Europäischen Wirtschaftsraum (im Folgenden \"EWR-Abkommen\"), insbesondere auf Art. 98,\nin Erwägung nachstehender Gründe:\n1. Die Durchführungsverordnung (EU) 2016/1936 der Kommission vom 4. November 2016 zur Genehmigung von Calciumoxid (gebranntem Kalk) als alten Wirkstoff zur Verwendung in Biozidprodukten der Produktarten 2 und 3 ist in das EWR-Abkommen aufzunehmen.\n2. Anhang II des EWR-Abkommens sollte daher entsprechend geändert werden -\nhat folgenden Beschluss erlassen:"
    }
  ],
  "definitions": []
}
