{
  "id": "li-konso-2019341000",
  "type": "statute",
  "title": "Kundmachung vom 10. Dezember 2019 des Beschlusses Nr. 37/2019 des Gemeinsamen EWR-Ausschusses",
  "title_en": "",
  "short_name": "LGBl 2019.341",
  "status": "in_force",
  "issued_date": "2019-12-10",
  "in_force_date": "2019-12-10",
  "url": "https://www.gesetze.li/konso/2019341000",
  "description": "Kundmachung vom 10. Dezember 2019 des Beschlusses Nr. 37/2019 des Gemeinsamen EWR-Ausschusses",
  "provisions": [
    {
      "provision_ref": "art1",
      "chapter": "Anhang",
      "section": "1",
      "title": "Art. 1",
      "content": "In Anhang IX des EWR-Abkommens wird unter Nummer 31bcs (Delegierte Verordnung (EU) 2016/2251 der Kommission) folgender Gedankenstrich angefügt:\n\"- 32019 R 0397 : Delegierte Verordnung (EU) 2019/397 der Kommission vom 19. Dezember 2018 (ABl. L 71 vom 13.3.2019, S. 15) \""
    },
    {
      "provision_ref": "art2",
      "chapter": "Anhang",
      "section": "2",
      "title": "Art. 2",
      "content": "Der Wortlaut der Delegierten Verordnung (EU) 2019/397 in isländischer und norwegischer Sprache, der in der EWR-Beilage des Amtsblattes der Europäischen Union veröffentlicht wird, ist verbindlich."
    },
    {
      "provision_ref": "art3",
      "chapter": "Anhang",
      "section": "3",
      "title": "Art. 3",
      "content": "Dieser Beschluss tritt am 29. März 2019 oder am Tag nach Eingang der letzten Mitteilung nach Art. 103 Abs. 1 des EWR-Abkommens oder am Tag des Inkrafttretens des Beschlusses des Gemeinsamen EWR-Ausschusses zur Aufnahme der Verordnung (EU) 2016/2251 in das EWR-Abkommen in Kraft, je nachdem, welcher Zeitpunkt der spätere ist."
    },
    {
      "provision_ref": "art4",
      "chapter": "Anhang",
      "section": "4",
      "title": "Art. 4",
      "content": "Dieser Beschluss wird im EWR-Abschnitt und in der EWR-Beilage des Amtsblattes der Europäischen Union veröffentlicht.\nGeschehen zu Brüssel am 29. März 2019.\n(Es folgen die Unterschriften)\n1\nABl. L 71 vom 13.3.2019, S. 15 .\n2\nEin Bestehen verfassungsrechtlicher Anforderungen wurde nicht mitgeteilt."
    }
  ],
  "definitions": []
}
